haystack_praisonai/__init__.py
haystack_praisonai/component.py
haystack_praisonai-0.1.0.dist-info/licenses/LICENSE
haystack_praisonai-0.1.0.dist-info/METADATA
haystack_praisonai-0.1.0.dist-info/WHEEL
haystack_praisonai-0.1.0.dist-info/top_level.txt
haystack_praisonai-0.1.0.dist-info/RECORD
