Metadata-Version: 2.4
Name: haystack-praisonai
Version: 0.1.0
Summary: Haystack integration for PraisonAI multi-agent framework
Author-email: Mervin Praison <support@praison.ai>
License-Expression: MIT
Project-URL: Homepage, https://github.com/MervinPraison/haystack-praisonai
Project-URL: Documentation, https://docs.praison.ai
Project-URL: Repository, https://github.com/MervinPraison/haystack-praisonai
Keywords: haystack,praisonai,ai-agents,multi-agent,llm,rag
Classifier: Development Status :: 4 - Beta
Classifier: Intended Audience :: Developers
Classifier: Programming Language :: Python :: 3
Classifier: Programming Language :: Python :: 3.9
Classifier: Programming Language :: Python :: 3.10
Classifier: Programming Language :: Python :: 3.11
Classifier: Programming Language :: Python :: 3.12
Requires-Python: >=3.9
License-File: LICENSE
Requires-Dist: haystack-ai>=2.0.0
Requires-Dist: httpx>=0.24.0
Provides-Extra: dev
Requires-Dist: pytest>=7.0.0; extra == "dev"
Requires-Dist: pytest-asyncio>=0.21.0; extra == "dev"
Requires-Dist: pytest-httpx>=0.21.0; extra == "dev"
Dynamic: license-file
